hourtrack-1.7.6.dist-info/licenses/LICENSE
src/hourtrack/__init__.py
src/hourtrack/hourtrack.py
src/hourtrack/utils/__init__.py
src/hourtrack/utils/argument_parser.py
src/hourtrack/utils/config.py
src/hourtrack/utils/helpers.py
src/hourtrack/utils/project_manager.py
hourtrack-1.7.6.dist-info/METADATA
hourtrack-1.7.6.dist-info/WHEEL
hourtrack-1.7.6.dist-info/entry_points.txt
hourtrack-1.7.6.dist-info/top_level.txt
hourtrack-1.7.6.dist-info/RECORD
