Metadata-Version: 2.4
Name: hourtrack
Version: 1.7.6
Summary: Python program that tracks total time spent on projects and saves sessions. It supports multiple projects.
Author-email: Rodrigo Martin Núñez <rodrigomartinnunez@gmail.com>
Maintainer-email: Rodrigo Martin Núñez <rodrigomartinnunez@gmail.com>
License: MIT License
Project-URL: Homepage, https://github.com/P-ict0/HourTrack.git
Project-URL: Bug Reports, https://github.com/P-ict0/HourTrack/issues
Keywords: hourtrack,time,track,projects,sessions,hours,minutes,seconds,time tracking,project tracking,session tracking,time management,project management,session management
Classifier: Development Status :: 3 - Alpha
Classifier: Intended Audience :: Developers
Classifier: Topic :: Software Development :: Build Tools
Classifier: License :: OSI Approved :: GNU General Public License v3 (GPLv3)
Classifier: Programming Language :: Python :: 3
Classifier: Programming Language :: Python :: 3.10
Classifier: Programming Language :: Python :: 3.11
Classifier: Programming Language :: Python :: 3.12
Classifier: Programming Language :: Python :: 3.13
Requires-Python: >=3.10
License-File: LICENSE
Dynamic: license-file
